BYOD/__init__.py
BYOD/context_sensitivity.py
BYOD/negations.py
BYOD/tokenization_robustness.py
BYOD/toxicity.py
BYOD/word_order.py
BYOD/List-of-Dirty-Naughty-Obscene-and-Otherwise-Bad-Words/en.txt
BYOD/utils/JSD.py
BYOD/utils/__init__.py
BYOD/utils/hf_utils.py
BYOD/utils/wikiDataset.py
BYOD-0.3.0.data/scripts/run_lrs.py
BYOD-0.3.0.data/scripts/run_negations.py
BYOD-0.3.0.data/scripts/run_tokenization_split.py
BYOD-0.3.0.data/scripts/run_toxicity.py
BYOD-0.3.0.data/scripts/run_word_order.py
BYOD-0.3.0.dist-info/METADATA
BYOD-0.3.0.dist-info/WHEEL
BYOD-0.3.0.dist-info/top_level.txt
BYOD-0.3.0.dist-info/RECORD
