Metadata-Version: 2.1
Name: BYOD
Version: 0.3.0
Summary: Bring Your Own Data! Self-Supervised Evaluation for Large Language Models
Home-page: https://github.com/neelsjain/BYOD
Author: Neel Jain, Khalid Saifullah, Jonas Geiping
Author-email: njain17@umd.edu
License: MIT
Keywords: todo
Platform: any
Classifier: Topic :: Scientific/Engineering :: Artificial Intelligence
Classifier: License :: OSI Approved :: MIT License
Classifier: Operating System :: OS Independent
Classifier: Programming Language :: Python
Requires-Python: >=3.9
Requires-Dist: torch (>=2.0.0)
Requires-Dist: transformers (>=4.28.1)
Requires-Dist: scipy (>=1.10.1)
Requires-Dist: datasets (>=2.11.0)
Requires-Dist: nltk (>=3.8.1)
Requires-Dist: apache-beam (>=2.48.0)
